authbox/__init__.py
authbox/api.py
authbox/badgereader_hid_keystroking.py
authbox/badgereader_wiegand_gpio.py
authbox/compat.py
authbox/config.py
authbox/fake_evdev_device_for_testing.py
authbox/fake_gpio_for_testing.py
authbox/gpio_button.py
authbox/gpio_buzzer.py
authbox/gpio_relay.py
authbox/timer.py
authbox-1.0.0.dist-info/LICENSE
authbox-1.0.0.dist-info/METADATA
authbox-1.0.0.dist-info/WHEEL
authbox-1.0.0.dist-info/top_level.txt
authbox-1.0.0.dist-info/RECORD
