Metadata-Version: 2.1
Name: authbox
Version: 1.0.0
Summary: A framework for makerspace tool/door authz/authn
Home-page: https://github.com/google/makerspace-auth
License: Apache2
Platform: linux
Requires-Python: >=2.7,!=3.0,!=3.1,!=3.2,!=3.3,!=3.4,!=3.5
